volviz/__init__.py
volviz/volviz.py
volviz-0.1.0.dist-info/METADATA
volviz-0.1.0.dist-info/WHEEL
volviz-0.1.0.dist-info/licenses/LICENSE
volviz-0.1.0.dist-info/RECORD
