Metadata-Version: 2.4
Name: volviz
Version: 0.1.0
Summary: Interactive 3D volume slicer for Jupyter Notebooks
Project-URL: Homepage, https://github.com/RJPaneque/volviz
Project-URL: Bug Tracker, https://github.com/RJPaneque/volviz/issues
Author-email: "Robert J. Paneque-Yunta" <rpaneque@ucm.es>
License: MIT License
License-File: LICENSE
Classifier: Framework :: Jupyter
Classifier: License :: OSI Approved :: MIT License
Classifier: Operating System :: OS Independent
Classifier: Programming Language :: Python :: 3
Requires-Python: >=3.7
Requires-Dist: ipympl
Requires-Dist: ipywidgets
Requires-Dist: matplotlib
Requires-Dist: numpy
